{
"pokemon":{
        "ID":148,
        "Name":"Dragonair",
        "Type":["Dragon"],
        "CatchRate":45,
        "GenderRatio":50,
		"Abilities":["Shed Skin", "Marvel Scale"],
        "EggGroups":["Water 1", "Dragon"],
        "HatchTime":[10455,10709],
        "Height":["13'01\"", "4.0 m"],
        "Weight":["36.4 lbs", "16.5 kg"],
        "RegionalPokedexNumbers":[303],
        "BaseExperienceYield":144,
        "LevelingRate":"Slow",
        "PokedexType":"Dragon Pokémon",
        "EVYield":{
            "HP":0,
            "ATK":2,
            "DEF":0,
            "SPATK":0,
            "SPDEF":0,
            "SPEED":0
        },
        "BodyStyle":2,
        "FootprintStyle":148,
        "PokedexColor":"Blue",
        "BaseFriendship":35,
        "Evolutions": [{"type":"level", "at":55, "into":"Dragonite"}],
        "PokedexEntry":"A Dragonair stores an enormous amount of energy inside its body. It is said to alter the weather around it by losing energy from the crystals on its neck and tail.",
		"HeldItems":[{"name":"Dragon Scale", "chance":5}],
        "BaseStats":{
            "HP":61,
            "ATK":84,
            "DEF":65,
            "SPATK":70,
            "SPDEF":70,
            "SPEED":70
        },
		"LearnSet":[
			{"level":0, "move":"Wrap"},
			{"level":0, "move":"Leer"},
			{"level":0, "move":"Thunder Wave"},
			{"level":0, "move":"Twister", "stab":1},
			{"level":8, "move":"Thunder Wave"},
			{"level":15, "move":"Twister", "stab":1},
			{"level":22, "move":"Dragon Rage"},
			{"level":29, "move":"Slam"},
			{"level":38, "move":"Agility"},
			{"level":47, "move":"Safeguard"},
			{"level":56, "move":"Outrage", "stab":1},
			{"level":65, "move":"Hyper Beam"},
			{"item":"TM03", "move":"Water Pulse"},
			{"item":"TM06", "move":"Toxic"},
			{"item":"TM07", "move":"Hail"},
			{"item":"TM10", "move":"Hidden Power"},
			{"item":"TM11", "move":"Sunny Day"},
			{"item":"TM13", "move":"Ice Beam"},
			{"item":"TM14", "move":"Blizzard"},
			{"item":"TM15", "move":"Hyper Beam"},
			{"item":"TM17", "move":"Protect"},
			{"item":"TM18", "move":"Rain Dance"},
			{"item":"TM20", "move":"Safeguard"},
			{"item":"TM21", "move":"Frustration"},
			{"item":"TM23", "move":"Iron Tail"},
			{"item":"TM24", "move":"Thunderbolt"},
			{"item":"TM25", "move":"Thunder"},
			{"item":"TM27", "move":"Return"},
			{"item":"TM32", "move":"Double Team"},
			{"item":"TM34", "move":"Shock Wave"},
			{"item":"TM35", "move":"Flamethrower"},
			{"item":"TM38", "move":"Fire Blast"},
			{"item":"TM42", "move":"Facade"},
			{"item":"TM43", "move":"Secret Power"},
			{"item":"TM44", "move":"Rest"},
			{"item":"TM45", "move":"Attract"},
			{"item":"HM03", "move":"Surf"},
			{"item":"HM07", "move":"Waterfall"}
		]
}
}