<?xml version="1.0" encoding="UTF-8"?>
<!-- Created with TexturePacker http://www.codeandweb.com/texturepacker-->
<!-- $TexturePacker:SmartUpdate:f47162e3334da9940bef7b11886639b5:8518835ed2690005f9eb5586d00e5f9c:d3370371052426d54f5a4d4e8f3d95da$ -->
<TextureAtlas imagePath="EHatMan2Male.png">
    <SubTexture name="walk_down01" x="2" y="1" width="16" height="21"/>
    <SubTexture name="walk_down03" x="2" y="1" width="16" height="21"/>
    <SubTexture name="walk_down02" x="20" y="2" width="16" height="21"/>
    <SubTexture name="walk_down04" x="38" y="2" width="16" height="21"/>
    <SubTexture name="walk_left01" x="56" y="1" width="16" height="21"/>
    <SubTexture name="walk_left03" x="56" y="1" width="16" height="21"/>
    <SubTexture name="walk_left02" x="74" y="2" width="16" height="21"/>
    <SubTexture name="walk_left04" x="92" y="2" width="16" height="21"/>
    <SubTexture name="walk_up01" x="110" y="1" width="16" height="21"/>
    <SubTexture name="walk_up03" x="110" y="1" width="16" height="21"/>
    <SubTexture name="walk_up02" x="128" y="2" width="16" height="21"/>
    <SubTexture name="walk_up04" x="146" y="2" width="16" height="21"/>
</TextureAtlas>
